{
  "commodity": "Drumstick",
  "train_score": 0.9994044303894043,
  "test_score": 0.9555734395980835,
  "mse": 83603.16002791269,
  "mae": 159.4724330357143,
  "rmse": 289.1421104369142,
  "mape": 1.7296844435135503,
  "n_samples": 136,
  "n_features": 24,
  "feature_names": [
    "min_price",
    "max_price",
    "temperature_2m_max",
    "temperature_2m_min",
    "precipitation_sum",
    "lat",
    "lon",
    "year",
    "month",
    "day_of_year",
    "week_of_year",
    "quarter",
    "is_spring",
    "is_summer",
    "is_monsoon",
    "is_winter",
    "seasonal_avg_price",
    "price_change",
    "price_change_7d",
    "price_change_30d",
    "price_ma_7",
    "price_ma_30",
    "price_std_7",
    "price_std_30"
  ],
  "trained_date": "2025-11-23T20:52:46.512459",
  "model_type": "XGBoost_Advanced"
}